wordcloud_fa/WordCloudFa.py
wordcloud_fa/__init__.py
wordcloud_fa/stopwords
wordcloud_fa/Fonts/font.ttf
wordcloud_fa-0.1.10.dist-info/LICENSE
wordcloud_fa-0.1.10.dist-info/METADATA
wordcloud_fa-0.1.10.dist-info/WHEEL
wordcloud_fa-0.1.10.dist-info/top_level.txt
wordcloud_fa-0.1.10.dist-info/RECORD
