Metadata-Version: 2.1
Name: wordcloud-fa
Version: 0.1.10
Summary: A wrapper for wordcloud module for creating persian (and other rtl languages) word cloud.
Home-page: https://github.com/alihoseiny/word_cloud_fa
Download-URL: https://github.com/alihoseiny/word_cloud_fa/archive/V0.1.10.tar.gz
Author: Mohammadreza Alihoseiny
Author-email: salam@alihoseiny.ir
License: MIT
Keywords: wordcloud,word cloud,Farsi,persian,Iran,nlp,National Language Processing,text processing,data visualization
License-File: LICENSE
Requires-Dist: numpy (>=1.18.1)
Requires-Dist: pillow (>=7.0.0)
Requires-Dist: matplotlib (>=3.1.2)
Requires-Dist: arabic-reshaper (>=2.1.3)
Requires-Dist: python-bidi (==0.4.2)
Requires-Dist: wordcloud (==1.8.2.2)
Requires-Dist: hazm (==0.7.0)
